streamlit_tetrascience_ui/__init__.py
streamlit_tetrascience_ui/components/packages/frontend/package.json
streamlit_tetrascience_ui/components/packages/frontend/dist/index.css
streamlit_tetrascience_ui/components/packages/frontend/dist/index.html
streamlit_tetrascience_ui/components/packages/frontend/dist/vite.svg
streamlit_tetrascience_ui/components/packages/frontend/dist/assets/index-DwK6V4b4.js
streamlit_tetrascience_ui/components/packages/frontend/dist/assets/index-zmuBz8hY.css
streamlit_tetrascience_ui/components/packages/frontend/dist/histogram_component/index.html
streamlit_tetrascience_ui/components/packages/streamlit-component-lib/package.json
streamlit_tetrascience_ui/components/packages/streamlit-component-lib/dist/ArrowTable.d.ts
streamlit_tetrascience_ui/components/packages/streamlit-component-lib/dist/ArrowTable.js
streamlit_tetrascience_ui/components/packages/streamlit-component-lib/dist/StreamlitReact.d.ts
streamlit_tetrascience_ui/components/packages/streamlit-component-lib/dist/StreamlitReact.js
streamlit_tetrascience_ui/components/packages/streamlit-component-lib/dist/index.d.ts
streamlit_tetrascience_ui/components/packages/streamlit-component-lib/dist/index.js
streamlit_tetrascience_ui/components/packages/streamlit-component-lib/dist/streamlit.d.ts
streamlit_tetrascience_ui/components/packages/streamlit-component-lib/dist/streamlit.js
streamlit_tetrascience_ui/components/packages/streamlit-component-lib/dist/test_utils.d.ts
streamlit_tetrascience_ui/components/packages/streamlit-component-lib/dist/test_utils.js
streamlit_tetrascience_ui/components/packages/ui/package.json
streamlit_tetrascience_ui/components/packages/ui/dist/index.css
streamlit_tetrascience_ui/components/packages/ui/dist/index.js
streamlit_tetrascience_ui/components/packages/ui/dist/cjs/App.d.ts
streamlit_tetrascience_ui/components/packages/ui/dist/cjs/index.d.ts
streamlit_tetrascience_ui/components/packages/ui/dist/cjs/index.js
tetrascience_streamlit_ui-0.2.0a0.dist-info/licenses/LICENSE
tetrascience_streamlit_ui-0.2.0a0.dist-info/METADATA
tetrascience_streamlit_ui-0.2.0a0.dist-info/WHEEL
tetrascience_streamlit_ui-0.2.0a0.dist-info/top_level.txt
tetrascience_streamlit_ui-0.2.0a0.dist-info/RECORD
