Metadata-Version: 2.4
Name: tetrascience-streamlit-ui
Version: 0.2.0a0
Summary: Use Tetrascience UI components in Streamlit
Home-page: https://github.com/tetrascience/ts-lib-ui-kit-streamlit
Author: TetraScience
Requires-Python: >=3.11,<3.12
License-File: LICENSE
Requires-Dist: streamlit<2.0.0,>=1.12.0
Requires-Dist: pydantic<3.0.0,>=2.0.0
Requires-Dist: polars<2.0.0,>=1.0.0
Requires-Dist: requests<3.0.0,>=2.25.0
Requires-Dist: snowflake-connector-python<4.0.0,>=3.0.0
Requires-Dist: databricks-sql-connector[pyarrow]<5.0.0,>=4.0.5
Requires-Dist: databricks-sdk<0.57.0,>=0.56.0
Requires-Dist: pyathena[arrow]<4.0.0,>=3.0.0
Requires-Dist: boto3<2.0.0,>=1.20.0
Requires-Dist: ts-sdk-connectors-python<3.0.0,>=2.0.0
Requires-Dist: pyjwt<3.0.0,>=2.8.0
Dynamic: author
Dynamic: description
Dynamic: description-content-type
Dynamic: home-page
Dynamic: license-file
Dynamic: requires-dist
Dynamic: requires-python
Dynamic: summary
